{"@components": {"actions": {"@id": "https://312.deporeibar.com/mendiak/acherito/111988501886238863343-2024-03-22/@actions"}, "aliases": {"@id": "https://312.deporeibar.com/mendiak/acherito/111988501886238863343-2024-03-22/@aliases"}, "breadcrumbs": {"@id": "https://312.deporeibar.com/mendiak/acherito/111988501886238863343-2024-03-22/@breadcrumbs"}, "contextnavigation": {"@id": "https://312.deporeibar.com/mendiak/acherito/111988501886238863343-2024-03-22/@contextnavigation"}, "navigation": {"@id": "https://312.deporeibar.com/mendiak/acherito/111988501886238863343-2024-03-22/@navigation"}, "navroot": {"@id": "https://312.deporeibar.com/mendiak/acherito/111988501886238863343-2024-03-22/@navroot"}, "types": {"@id": "https://312.deporeibar.com/mendiak/acherito/111988501886238863343-2024-03-22/@types"}, "workflow": {"@id": "https://312.deporeibar.com/mendiak/acherito/111988501886238863343-2024-03-22/@workflow"}}, "@id": "https://312.deporeibar.com/mendiak/acherito/111988501886238863343-2024-03-22", "@type": "Igoera", "UID": "1d5645325f2e4e81a12c380fdfb8f75d", "allow_discussion": false, "contributors": [], "created": "2024-03-22T16:32:38+00:00", "creators": ["111988501886238863343"], "description": "", "effective": null, "egindako_eguna": null, "egoera": {"title": "Bertan behera utzita", "token": "bertan-behera"}, "eguna": "2024-06-15", "exclude_from_nav": false, "expires": null, "id": "111988501886238863343-2024-03-22", "is_folderish": true, "items": [], "items_total": 0, "language": "", "layout": "view", "lock": {"locked": false, "stealable": true}, "mendia_igo_duena": "", "mendizaleak": null, "modified": "2024-06-25T05:30:23+00:00", "next_item": {}, "oharrak": "Atxerito eskalatzen igoko dugu ", "parent": {"@id": "https://312.deporeibar.com/mendiak/acherito", "@type": "Mendia", "altuera": 2374, "created": "2024-03-11T21:18:07+00:00", "creators": ["admin"], "description": "", "egoera_igoera": null, "egoera_mendia": null, "eguna": null, "erreserbak": null, "image_field": null, "image_scales": {}, "lat": "42.8914482", "lon": "-0.7372228", "mendizerra": "Pirinioak", "review_state": "published", "sektorea": "Huesca", "title": "Acherito", "type_title": "Mendia", "zailtasuna": 1}, "previous_item": {}, "review_state": "published", "rights": "", "subjects": [], "title": "111988501886238863343 - 2024-03-22", "type_title": "Igoera", "version": "current", "working_copy": null, "working_copy_of": null}