{"@components": {"actions": {"@id": "https://312.deporeibar.com/mendiak/pico-de-aspe/115986176105195498751-2024-07-1/@actions"}, "aliases": {"@id": "https://312.deporeibar.com/mendiak/pico-de-aspe/115986176105195498751-2024-07-1/@aliases"}, "breadcrumbs": {"@id": "https://312.deporeibar.com/mendiak/pico-de-aspe/115986176105195498751-2024-07-1/@breadcrumbs"}, "contextnavigation": {"@id": "https://312.deporeibar.com/mendiak/pico-de-aspe/115986176105195498751-2024-07-1/@contextnavigation"}, "navigation": {"@id": "https://312.deporeibar.com/mendiak/pico-de-aspe/115986176105195498751-2024-07-1/@navigation"}, "navroot": {"@id": "https://312.deporeibar.com/mendiak/pico-de-aspe/115986176105195498751-2024-07-1/@navroot"}, "types": {"@id": "https://312.deporeibar.com/mendiak/pico-de-aspe/115986176105195498751-2024-07-1/@types"}, "workflow": {"@id": "https://312.deporeibar.com/mendiak/pico-de-aspe/115986176105195498751-2024-07-1/@workflow"}}, "@id": "https://312.deporeibar.com/mendiak/pico-de-aspe/115986176105195498751-2024-07-1", "@type": "Igoera", "UID": "7c044bd42adf473bbe0d3a8ad5c5a283", "allow_discussion": false, "contributors": [], "created": "2024-07-01T17:12:54+00:00", "creators": ["115986176105195498751"], "description": "", "effective": null, "egindako_eguna": null, "egoera": {"title": "Bertan behera utzita", "token": "bertan-behera"}, "eguna": "2024-07-07", "exclude_from_nav": false, "expires": null, "id": "115986176105195498751-2024-07-1", "is_folderish": true, "items": [], "items_total": 0, "language": "", "layout": "view", "lock": {"locked": false, "stealable": true}, "mendia_igo_duena": "", "mendizaleak": null, "modified": "2024-07-12T10:43:59+00:00", "next_item": {}, "oharrak": "KKT Irteera, Igor Azurmendikin", "parent": {"@id": "https://312.deporeibar.com/mendiak/pico-de-aspe", "@type": "Mendia", "altuera": 2640, "created": "2024-03-11T21:18:23+00:00", "creators": ["admin"], "description": "", "egoera_igoera": null, "egoera_mendia": null, "eguna": null, "erreserbak": null, "image_field": null, "image_scales": {}, "lat": "42.7634819", "lon": "-0.5657495", "mendizerra": "Pirinioak", "review_state": "published", "sektorea": "Huesca", "title": "Pico de Aspe", "type_title": "Mendia", "zailtasuna": 1}, "previous_item": {}, "review_state": "published", "rights": "", "subjects": [], "title": "115986176105195498751 - 2024-07-1", "type_title": "Igoera", "version": "current", "working_copy": null, "working_copy_of": null}