{"@components": {"actions": {"@id": "https://312.deporeibar.com/mendiak/punta-de-treserols-monte-perdido/110267514905115121201-2024-07-31/@actions"}, "aliases": {"@id": "https://312.deporeibar.com/mendiak/punta-de-treserols-monte-perdido/110267514905115121201-2024-07-31/@aliases"}, "breadcrumbs": {"@id": "https://312.deporeibar.com/mendiak/punta-de-treserols-monte-perdido/110267514905115121201-2024-07-31/@breadcrumbs"}, "contextnavigation": {"@id": "https://312.deporeibar.com/mendiak/punta-de-treserols-monte-perdido/110267514905115121201-2024-07-31/@contextnavigation"}, "navigation": {"@id": "https://312.deporeibar.com/mendiak/punta-de-treserols-monte-perdido/110267514905115121201-2024-07-31/@navigation"}, "navroot": {"@id": "https://312.deporeibar.com/mendiak/punta-de-treserols-monte-perdido/110267514905115121201-2024-07-31/@navroot"}, "types": {"@id": "https://312.deporeibar.com/mendiak/punta-de-treserols-monte-perdido/110267514905115121201-2024-07-31/@types"}, "workflow": {"@id": "https://312.deporeibar.com/mendiak/punta-de-treserols-monte-perdido/110267514905115121201-2024-07-31/@workflow"}}, "@id": "https://312.deporeibar.com/mendiak/punta-de-treserols-monte-perdido/110267514905115121201-2024-07-31", "@type": "Igoera", "UID": "c0d5695f25b749a784cf12097005b6d3", "allow_discussion": false, "contributors": [], "created": "2024-07-31T07:34:01+00:00", "creators": ["110267514905115121201"], "description": "", "effective": null, "egindako_eguna": null, "egoera": {"title": "Bertan behera utzita", "token": "bertan-behera"}, "eguna": "2024-08-03", "exclude_from_nav": false, "expires": null, "id": "110267514905115121201-2024-07-31", "is_folderish": true, "items": [], "items_total": 0, "language": "", "layout": "view", "lock": {"locked": false, "stealable": true}, "mendia_igo_duena": "", "mendizaleak": null, "modified": "2024-08-05T07:22:09+00:00", "next_item": {}, "oharrak": "Sonia Larra\u00f1agarekin noa", "parent": {"@id": "https://312.deporeibar.com/mendiak/punta-de-treserols-monte-perdido", "@type": "Mendia", "altuera": 3355, "created": "2024-03-11T21:18:33+00:00", "creators": ["admin"], "description": "", "egoera_igoera": null, "egoera_mendia": null, "eguna": null, "erreserbak": null, "image_field": null, "image_scales": {}, "lat": "42.6755485", "lon": "0.0343568", "mendizerra": "Pirinioak", "review_state": "published", "sektorea": "Monte Perdido", "title": "Punta de Treserols / Monte Perdido", "type_title": "Mendia", "zailtasuna": 1}, "previous_item": {}, "review_state": "published", "rights": "", "subjects": [], "title": "110267514905115121201 - 2024-07-31", "type_title": "Igoera", "version": "current", "working_copy": null, "working_copy_of": null}