{"@components": {"actions": {"@id": "https://312.deporeibar.com/beste-igoerak/castro-grande/@actions"}, "aliases": {"@id": "https://312.deporeibar.com/beste-igoerak/castro-grande/@aliases"}, "breadcrumbs": {"@id": "https://312.deporeibar.com/beste-igoerak/castro-grande/@breadcrumbs"}, "contextnavigation": {"@id": "https://312.deporeibar.com/beste-igoerak/castro-grande/@contextnavigation"}, "navigation": {"@id": "https://312.deporeibar.com/beste-igoerak/castro-grande/@navigation"}, "navroot": {"@id": "https://312.deporeibar.com/beste-igoerak/castro-grande/@navroot"}, "types": {"@id": "https://312.deporeibar.com/beste-igoerak/castro-grande/@types"}, "workflow": {"@id": "https://312.deporeibar.com/beste-igoerak/castro-grande/@workflow"}}, "@id": "https://312.deporeibar.com/beste-igoerak/castro-grande", "@type": "Mendia", "UID": "11141bad92db484787510970988f38e5", "allow_discussion": false, "altuera": 1094, "beste_izenak": "", "contributors": [], "created": "2024-10-06T16:55:09+00:00", "creators": ["106932265020763600836"], "description": "", "effective": "2024-10-11T15:37:04", "egoera": "eginda", "exclude_from_nav": false, "expires": null, "id": "castro-grande", "image": null, "image_caption": null, "is_folderish": true, "items": [{"@components": {"actions": {"@id": "https://312.deporeibar.com/beste-igoerak/castro-grande/krabelin-taldea/@actions"}, "aliases": {"@id": "https://312.deporeibar.com/beste-igoerak/castro-grande/krabelin-taldea/@aliases"}, "breadcrumbs": {"@id": "https://312.deporeibar.com/beste-igoerak/castro-grande/krabelin-taldea/@breadcrumbs"}, "contextnavigation": {"@id": "https://312.deporeibar.com/beste-igoerak/castro-grande/krabelin-taldea/@contextnavigation"}, "navigation": {"@id": "https://312.deporeibar.com/beste-igoerak/castro-grande/krabelin-taldea/@navigation"}, "navroot": {"@id": "https://312.deporeibar.com/beste-igoerak/castro-grande/krabelin-taldea/@navroot"}, "types": {"@id": "https://312.deporeibar.com/beste-igoerak/castro-grande/krabelin-taldea/@types"}, "workflow": {"@id": "https://312.deporeibar.com/beste-igoerak/castro-grande/krabelin-taldea/@workflow"}}, "@id": "https://312.deporeibar.com/beste-igoerak/castro-grande/krabelin-taldea", "@type": "Igoera", "UID": "129b83e547c242f6aaa53e6dcf77f315", "allow_discussion": false, "contributors": [], "created": "2024-10-06T16:56:41+00:00", "creators": ["106932265020763600836"], "description": "", "effective": "2024-10-11T15:37:05", "egindako_eguna": "2024-09-23", "egoera": {"title": "Eginda", "token": "eginda"}, "eguna": "2024-09-23", "exclude_from_nav": false, "expires": null, "id": "krabelin-taldea", "is_folderish": true, "language": {"title": "Euskara", "token": "eu"}, "layout": "view", "lock": {"locked": false, "stealable": true}, "mendia_igo_duena": "Krabelin taldea", "mendizaleak": "Javi \u00c1vila\nAnt\u00f3n Azpiazu\nAlfonso Moya\nLuis M. Pintado\n\u00c1ngel Trevi\u00f1o\nJavier Basterrika\nFernando Zuazua\nInaxio Abanzabalegi\nJuli\u00e1n Echeverria", "modified": "2024-10-11T13:37:05+00:00", "next_item": {}, "oharrak": "", "parent": {"@id": "https://312.deporeibar.com/beste-igoerak/castro-grande", "@type": "Mendia", "altuera": 1094, "created": "2024-10-06T16:55:09+00:00", "creators": ["106932265020763600836"], "description": "", "egoera_igoera": null, "egoera_mendia": null, "eguna": null, "erreserbak": null, "image_field": null, "image_scales": {}, "lat": "43.0896558", "lon": "-3.2234740", "mendizerra": "Burgosko mendiak", "review_state": "published", "sektorea": "Burgos", "title": "Castro grande", "type_title": "Mendia", "zailtasuna": 1}, "previous_item": {}, "review_state": "published", "rights": "", "subjects": [], "title": "Krabelin taldea", "type_title": "Igoera", "version": "current", "working_copy": null, "working_copy_of": null}], "items_total": 1, "language": {"title": "Euskara", "token": "eu"}, "lat": "43.0896558", "layout": "view", "lock": {"locked": false, "stealable": true}, "lon": "-3.2234740", "mendizerra": "Burgosko mendiak", "modified": "2024-10-11T13:37:04+00:00", "next_item": {}, "osm_kodea": "948582049", "parent": {"@id": "https://312.deporeibar.com/beste-igoerak", "@type": "Document", "altuera": null, "created": "2024-10-10T09:00:39+00:00", "creators": ["106932265020763600836"], "description": "", "egoera_igoera": null, "egoera_mendia": null, "eguna": null, "erreserbak": null, "image_field": null, "image_scales": {}, "lat": null, "lon": null, "mendizerra": null, "review_state": "published", "sektorea": null, "title": "Beste igoerak", "type_title": "Orria", "zailtasuna": null}, "previous_item": {}, "review_state": "published", "rights": "", "sektorea": "Burgos", "subjects": [], "title": "Castro grande", "type_title": "Mendia", "version": "current", "working_copy": null, "working_copy_of": null, "zailtasuna": 1}