{"@components": {"actions": {"@id": "https://312.deporeibar.com/mendiak/la-alcazaba/@actions"}, "aliases": {"@id": "https://312.deporeibar.com/mendiak/la-alcazaba/@aliases"}, "breadcrumbs": {"@id": "https://312.deporeibar.com/mendiak/la-alcazaba/@breadcrumbs"}, "contextnavigation": {"@id": "https://312.deporeibar.com/mendiak/la-alcazaba/@contextnavigation"}, "navigation": {"@id": "https://312.deporeibar.com/mendiak/la-alcazaba/@navigation"}, "navroot": {"@id": "https://312.deporeibar.com/mendiak/la-alcazaba/@navroot"}, "types": {"@id": "https://312.deporeibar.com/mendiak/la-alcazaba/@types"}, "workflow": {"@id": "https://312.deporeibar.com/mendiak/la-alcazaba/@workflow"}}, "@id": "https://312.deporeibar.com/mendiak/la-alcazaba", "@type": "Mendia", "UID": "80196da15a0448c885bf624adeedcac3", "allow_discussion": false, "altuera": 3369, "beste_izenak": "\n\n\n\n\n\n\n\n\n\n\n\n\n\n\n\n\n\n", "contributors": [], "created": "2024-03-11T21:18:29+00:00", "creators": ["admin"], "description": "", "effective": "2024-03-11T22:21:53", "egoera": "egin-gabe", "exclude_from_nav": false, "expires": null, "id": "la-alcazaba", "image": null, "image_caption": null, "is_folderish": true, "items": [], "items_total": 0, "language": "", "lat": "37.0678659", "layout": "view", "lock": {"locked": false, "stealable": true}, "lon": "-3.3011576", "mendizerra": "Penibetikoa", "modified": "2024-03-11T21:21:53+00:00", "next_item": {}, "osm_kodea": "937910053", "parent": {"@id": "https://312.deporeibar.com/mendiak", "@type": "Document", "altuera": null, "created": "2024-02-19T19:25:17+00:00", "creators": ["admin"], "description": "", "egoera_igoera": null, "egoera_mendia": null, "eguna": null, "erreserbak": null, "image_field": null, "image_scales": {}, "lat": null, "lon": null, "mendizerra": null, "review_state": "published", "sektorea": null, "title": "Mendiak", "type_title": "Orria", "zailtasuna": null}, "previous_item": {}, "review_state": "published", "rights": "", "sektorea": "Granada", "subjects": [], "title": "La Alcazaba", "type_title": "Mendia", "version": "current", "working_copy": null, "working_copy_of": null, "zailtasuna": 1}