{"@components": {"actions": {"@id": "https://312.deporeibar.com/mendiak/lescarpu-ou-pic-de-sesques/@actions"}, "aliases": {"@id": "https://312.deporeibar.com/mendiak/lescarpu-ou-pic-de-sesques/@aliases"}, "breadcrumbs": {"@id": "https://312.deporeibar.com/mendiak/lescarpu-ou-pic-de-sesques/@breadcrumbs"}, "contextnavigation": {"@id": "https://312.deporeibar.com/mendiak/lescarpu-ou-pic-de-sesques/@contextnavigation"}, "navigation": {"@id": "https://312.deporeibar.com/mendiak/lescarpu-ou-pic-de-sesques/@navigation"}, "navroot": {"@id": "https://312.deporeibar.com/mendiak/lescarpu-ou-pic-de-sesques/@navroot"}, "types": {"@id": "https://312.deporeibar.com/mendiak/lescarpu-ou-pic-de-sesques/@types"}, "workflow": {"@id": "https://312.deporeibar.com/mendiak/lescarpu-ou-pic-de-sesques/@workflow"}}, "@id": "https://312.deporeibar.com/mendiak/lescarpu-ou-pic-de-sesques", "@type": "Mendia", "UID": "18b5f5780b9b4978970563f3056d0ad5", "allow_discussion": false, "altuera": 2606, "beste_izenak": "\n\n\n\n\n\n\n\n\n\n\n\n\n\n\n\n\n\n", "contributors": [], "created": "2024-03-11T21:18:27+00:00", "creators": ["admin"], "description": "", "effective": "2024-03-11T22:21:35", "egoera": "eginda", "exclude_from_nav": false, "expires": null, "id": "lescarpu-ou-pic-de-sesques", "image": null, "image_caption": null, "is_folderish": true, "items": [{"@components": {"actions": {"@id": "https://312.deporeibar.com/mendiak/lescarpu-ou-pic-de-sesques/103053371365584180910-2024-07-13/@actions"}, "aliases": {"@id": "https://312.deporeibar.com/mendiak/lescarpu-ou-pic-de-sesques/103053371365584180910-2024-07-13/@aliases"}, "breadcrumbs": {"@id": "https://312.deporeibar.com/mendiak/lescarpu-ou-pic-de-sesques/103053371365584180910-2024-07-13/@breadcrumbs"}, "contextnavigation": {"@id": "https://312.deporeibar.com/mendiak/lescarpu-ou-pic-de-sesques/103053371365584180910-2024-07-13/@contextnavigation"}, "navigation": {"@id": "https://312.deporeibar.com/mendiak/lescarpu-ou-pic-de-sesques/103053371365584180910-2024-07-13/@navigation"}, "navroot": {"@id": "https://312.deporeibar.com/mendiak/lescarpu-ou-pic-de-sesques/103053371365584180910-2024-07-13/@navroot"}, "types": {"@id": "https://312.deporeibar.com/mendiak/lescarpu-ou-pic-de-sesques/103053371365584180910-2024-07-13/@types"}, "workflow": {"@id": "https://312.deporeibar.com/mendiak/lescarpu-ou-pic-de-sesques/103053371365584180910-2024-07-13/@workflow"}}, "@id": "https://312.deporeibar.com/mendiak/lescarpu-ou-pic-de-sesques/103053371365584180910-2024-07-13", "@type": "Igoera", "UID": "e7f68955f0da4abdacd9883865a4778f", "allow_discussion": false, "contributors": [], "created": "2024-07-13T04:42:23+00:00", "creators": ["103053371365584180910"], "description": "", "effective": null, "egindako_eguna": "2024-07-13", "egoera": {"title": "Eginda", "token": "eginda"}, "eguna": "2024-07-14", "exclude_from_nav": false, "expires": null, "id": "103053371365584180910-2024-07-13", "is_folderish": true, "language": "", "layout": "view", "lock": {"locked": false, "stealable": true}, "mendia_igo_duena": "", "mendizaleak": "Ander Gisasola\nMikel Echebarria", "modified": "2024-07-14T18:20:18+00:00", "next_item": {}, "oharrak": "Ander Gisasolakin, Etsautetik", "parent": {"@id": "https://312.deporeibar.com/mendiak/lescarpu-ou-pic-de-sesques", "@type": "Mendia", "altuera": 2606, "created": "2024-03-11T21:18:27+00:00", "creators": ["admin"], "description": "", "egoera_igoera": null, "egoera_mendia": null, "eguna": null, "erreserbak": null, "image_field": null, "image_scales": {}, "lat": "42.9191814", "lon": "-0.5037737", "mendizerra": "Pirinioak", "review_state": "published", "sektorea": "Pirinio Atlantikoak", "title": "L'Escarpu ou Pic de Sesques", "type_title": "Mendia", "zailtasuna": 1}, "previous_item": {}, "review_state": "published", "rights": "", "subjects": [], "title": "103053371365584180910 - 2024-07-13", "type_title": "Igoera", "version": "current", "working_copy": null, "working_copy_of": null}], "items_total": 1, "language": "", "lat": "42.9191814", "layout": "view", "lock": {"locked": false, "stealable": true}, "lon": "-0.5037737", "mendizerra": "Pirinioak", "modified": "2024-07-14T18:19:43+00:00", "next_item": {}, "osm_kodea": "732725482", "parent": {"@id": "https://312.deporeibar.com/mendiak", "@type": "Document", "altuera": null, "created": "2024-02-19T19:25:17+00:00", "creators": ["admin"], "description": "", "egoera_igoera": null, "egoera_mendia": null, "eguna": null, "erreserbak": null, "image_field": null, "image_scales": {}, "lat": null, "lon": null, "mendizerra": null, "review_state": "published", "sektorea": null, "title": "Mendiak", "type_title": "Orria", "zailtasuna": null}, "previous_item": {}, "review_state": "published", "rights": "", "sektorea": "Pirinio Atlantikoak", "subjects": [], "title": "L'Escarpu ou Pic de Sesques", "type_title": "Mendia", "version": "current", "working_copy": null, "working_copy_of": null, "zailtasuna": 1}