{"@components": {"actions": {"@id": "https://312.deporeibar.com/mendiak/puttarri/@actions"}, "aliases": {"@id": "https://312.deporeibar.com/mendiak/puttarri/@aliases"}, "breadcrumbs": {"@id": "https://312.deporeibar.com/mendiak/puttarri/@breadcrumbs"}, "contextnavigation": {"@id": "https://312.deporeibar.com/mendiak/puttarri/@contextnavigation"}, "navigation": {"@id": "https://312.deporeibar.com/mendiak/puttarri/@navigation"}, "navroot": {"@id": "https://312.deporeibar.com/mendiak/puttarri/@navroot"}, "types": {"@id": "https://312.deporeibar.com/mendiak/puttarri/@types"}, "workflow": {"@id": "https://312.deporeibar.com/mendiak/puttarri/@workflow"}}, "@id": "https://312.deporeibar.com/mendiak/puttarri", "@type": "Mendia", "UID": "aff2d27d9e024f00ac879c85837a1812", "allow_discussion": false, "altuera": 1299, "beste_izenak": "\n\n\n\n\n\n\n\n\n\n\n\n\n\n\n\n\n\n", "contributors": [], "created": "2024-03-11T21:18:31+00:00", "creators": ["admin"], "description": "", "effective": "2024-03-11T22:21:54", "egoera": "eginda", "exclude_from_nav": false, "expires": null, "id": "puttarri", "image": null, "image_caption": null, "is_folderish": true, "items": [{"@components": {"actions": {"@id": "https://312.deporeibar.com/mendiak/puttarri/112544487536596131199-2024-04-12/@actions"}, "aliases": {"@id": "https://312.deporeibar.com/mendiak/puttarri/112544487536596131199-2024-04-12/@aliases"}, "breadcrumbs": {"@id": "https://312.deporeibar.com/mendiak/puttarri/112544487536596131199-2024-04-12/@breadcrumbs"}, "contextnavigation": {"@id": "https://312.deporeibar.com/mendiak/puttarri/112544487536596131199-2024-04-12/@contextnavigation"}, "navigation": {"@id": "https://312.deporeibar.com/mendiak/puttarri/112544487536596131199-2024-04-12/@navigation"}, "navroot": {"@id": "https://312.deporeibar.com/mendiak/puttarri/112544487536596131199-2024-04-12/@navroot"}, "types": {"@id": "https://312.deporeibar.com/mendiak/puttarri/112544487536596131199-2024-04-12/@types"}, "workflow": {"@id": "https://312.deporeibar.com/mendiak/puttarri/112544487536596131199-2024-04-12/@workflow"}}, "@id": "https://312.deporeibar.com/mendiak/puttarri/112544487536596131199-2024-04-12", "@type": "Igoera", "UID": "e5a2b9ee48054196baa215021e25296c", "allow_discussion": false, "contributors": [], "created": "2024-04-12T09:11:48+00:00", "creators": ["112544487536596131199"], "description": "", "effective": null, "egindako_eguna": "2024-04-12", "egoera": {"title": "Eginda", "token": "eginda"}, "eguna": "2024-04-13", "exclude_from_nav": false, "expires": null, "id": "112544487536596131199-2024-04-12", "is_folderish": true, "language": "", "layout": "view", "lock": {"locked": false, "stealable": true}, "mendia_igo_duena": "", "mendizaleak": "Marialui Zendoia \nAntton Aldalur", "modified": "2024-04-27T17:05:19+00:00", "next_item": {}, "oharrak": "Aurrez erresernatu gabe egin dugu, libre zegoela ikusits", "parent": {"@id": "https://312.deporeibar.com/mendiak/puttarri", "@type": "Mendia", "altuera": 1299, "created": "2024-03-11T21:18:31+00:00", "creators": ["admin"], "description": "", "egoera_igoera": null, "egoera_mendia": null, "eguna": null, "erreserbak": null, "image_field": null, "image_scales": {}, "lat": "42.9704002", "lon": "-2.0567401", "mendizerra": "Euskal Herriko Mendiak", "review_state": "published", "sektorea": "Gipuzkoa", "title": "Puttarri", "type_title": "Mendia", "zailtasuna": 1}, "previous_item": {}, "review_state": "published", "rights": "", "subjects": [], "title": "112544487536596131199 - 2024-04-12", "type_title": "Igoera", "version": "current", "working_copy": null, "working_copy_of": null}, {"@components": {"actions": {"@id": "https://312.deporeibar.com/mendiak/puttarri/irteera/@actions"}, "aliases": {"@id": "https://312.deporeibar.com/mendiak/puttarri/irteera/@aliases"}, "breadcrumbs": {"@id": "https://312.deporeibar.com/mendiak/puttarri/irteera/@breadcrumbs"}, "contextnavigation": {"@id": "https://312.deporeibar.com/mendiak/puttarri/irteera/@contextnavigation"}, "navigation": {"@id": "https://312.deporeibar.com/mendiak/puttarri/irteera/@navigation"}, "navroot": {"@id": "https://312.deporeibar.com/mendiak/puttarri/irteera/@navroot"}, "types": {"@id": "https://312.deporeibar.com/mendiak/puttarri/irteera/@types"}, "workflow": {"@id": "https://312.deporeibar.com/mendiak/puttarri/irteera/@workflow"}}, "@id": "https://312.deporeibar.com/mendiak/puttarri/irteera", "@type": "Igoera", "UID": "f36080fe6f1a4f57a388bcf0b71e83d3", "allow_discussion": false, "contributors": [], "created": "2024-11-14T16:21:50+00:00", "creators": ["106932265020763600836"], "description": "", "effective": "2024-11-14T16:21:54", "egindako_eguna": "2024-11-09", "egoera": {"title": "Eginda", "token": "eginda"}, "eguna": "2024-11-09", "exclude_from_nav": false, "expires": null, "id": "irteera", "is_folderish": true, "language": {"title": "Euskara", "token": "eu"}, "layout": "view", "lock": {"locked": false, "stealable": true}, "mendia_igo_duena": null, "mendizaleak": "Fernando  Zuazua\nJosean Legarda\nJes\u00fas Garate\nIgnacio Abanzabalegi\nKike Albistegi\n", "modified": "2024-11-14T16:22:25+00:00", "next_item": {}, "oharrak": "", "parent": {"@id": "https://312.deporeibar.com/mendiak/puttarri", "@type": "Mendia", "altuera": 1299, "created": "2024-03-11T21:18:31+00:00", "creators": ["admin"], "description": "", "egoera_igoera": null, "egoera_mendia": null, "eguna": null, "erreserbak": null, "image_field": null, "image_scales": {}, "lat": "42.9704002", "lon": "-2.0567401", "mendizerra": "Euskal Herriko Mendiak", "review_state": "published", "sektorea": "Gipuzkoa", "title": "Puttarri", "type_title": "Mendia", "zailtasuna": 1}, "previous_item": {}, "review_state": "published", "rights": "", "subjects": [], "title": "Irteera", "type_title": "Igoera", "version": "current", "working_copy": null, "working_copy_of": null}], "items_total": 2, "language": "", "lat": "42.9704002", "layout": "view", "lock": {"locked": false, "stealable": true}, "lon": "-2.0567401", "mendizerra": "Euskal Herriko Mendiak", "modified": "2024-11-14T16:21:51+00:00", "next_item": {}, "osm_kodea": "948492264", "parent": {"@id": "https://312.deporeibar.com/mendiak", "@type": "Document", "altuera": null, "created": "2024-02-19T19:25:17+00:00", "creators": ["admin"], "description": "", "egoera_igoera": null, "egoera_mendia": null, "eguna": null, "erreserbak": null, "image_field": null, "image_scales": {}, "lat": null, "lon": null, "mendizerra": null, "review_state": "published", "sektorea": null, "title": "Mendiak", "type_title": "Orria", "zailtasuna": null}, "previous_item": {}, "review_state": "published", "rights": "", "sektorea": "Gipuzkoa", "subjects": [], "title": "Puttarri", "type_title": "Mendia", "version": "current", "working_copy": null, "working_copy_of": null, "zailtasuna": 1}