{"@components": {"actions": {"@id": "https://312.deporeibar.com/mendiak/roche-ecrite/@actions"}, "aliases": {"@id": "https://312.deporeibar.com/mendiak/roche-ecrite/@aliases"}, "breadcrumbs": {"@id": "https://312.deporeibar.com/mendiak/roche-ecrite/@breadcrumbs"}, "contextnavigation": {"@id": "https://312.deporeibar.com/mendiak/roche-ecrite/@contextnavigation"}, "navigation": {"@id": "https://312.deporeibar.com/mendiak/roche-ecrite/@navigation"}, "navroot": {"@id": "https://312.deporeibar.com/mendiak/roche-ecrite/@navroot"}, "types": {"@id": "https://312.deporeibar.com/mendiak/roche-ecrite/@types"}, "workflow": {"@id": "https://312.deporeibar.com/mendiak/roche-ecrite/@workflow"}}, "@id": "https://312.deporeibar.com/mendiak/roche-ecrite", "@type": "Mendia", "UID": "27e17ab054f348f699605468c49267a7", "allow_discussion": false, "altuera": 2276, "beste_izenak": "", "contributors": [], "created": "2024-10-20T16:16:10+00:00", "creators": ["106932265020763600836"], "description": "", "effective": "2024-10-20T18:16:15", "egoera": "proposatutakoa-eginda", "exclude_from_nav": false, "expires": null, "id": "roche-ecrite", "image": null, "image_caption": null, "is_folderish": true, "items": [{"@components": {"actions": {"@id": "https://312.deporeibar.com/mendiak/roche-ecrite/agustin-y-cia/@actions"}, "aliases": {"@id": "https://312.deporeibar.com/mendiak/roche-ecrite/agustin-y-cia/@aliases"}, "breadcrumbs": {"@id": "https://312.deporeibar.com/mendiak/roche-ecrite/agustin-y-cia/@breadcrumbs"}, "contextnavigation": {"@id": "https://312.deporeibar.com/mendiak/roche-ecrite/agustin-y-cia/@contextnavigation"}, "navigation": {"@id": "https://312.deporeibar.com/mendiak/roche-ecrite/agustin-y-cia/@navigation"}, "navroot": {"@id": "https://312.deporeibar.com/mendiak/roche-ecrite/agustin-y-cia/@navroot"}, "types": {"@id": "https://312.deporeibar.com/mendiak/roche-ecrite/agustin-y-cia/@types"}, "workflow": {"@id": "https://312.deporeibar.com/mendiak/roche-ecrite/agustin-y-cia/@workflow"}}, "@id": "https://312.deporeibar.com/mendiak/roche-ecrite/agustin-y-cia", "@type": "Igoera", "UID": "bfd3d4f5fa7c40b999e4f743d6d30767", "allow_discussion": false, "contributors": [], "created": "2024-10-20T16:16:46+00:00", "creators": ["106932265020763600836"], "description": "", "effective": "2024-10-20T18:16:51", "egindako_eguna": "2024-10-09", "egoera": {"title": "Proposatutakoa eginda", "token": "proposatutakoa-eginda"}, "eguna": "2024-10-09", "exclude_from_nav": false, "expires": null, "id": "agustin-y-cia", "is_folderish": true, "language": {"title": "Euskara", "token": "eu"}, "layout": "view", "lock": {"locked": false, "stealable": true}, "mendia_igo_duena": null, "mendizaleak": "Agustin Lamariano\nAndoni Basabe\nAlberto Alava", "modified": "2024-10-20T16:17:14+00:00", "next_item": {}, "oharrak": "", "parent": {"@id": "https://312.deporeibar.com/mendiak/roche-ecrite", "@type": "Mendia", "altuera": 2276, "created": "2024-10-20T16:16:10+00:00", "creators": ["106932265020763600836"], "description": "", "egoera_igoera": null, "egoera_mendia": null, "eguna": null, "erreserbak": null, "image_field": null, "image_scales": {}, "lat": "-21.0150290", "lon": "55.4610819", "mendizerra": "Reunion", "review_state": "published", "sektorea": "Reunion", "title": "Roche \u00c9crite", "type_title": "Mendia", "zailtasuna": 1}, "previous_item": {}, "review_state": "published", "rights": "", "subjects": [], "title": "Agustin y cia", "type_title": "Igoera", "version": "current", "working_copy": null, "working_copy_of": null}], "items_total": 1, "language": {"title": "Euskara", "token": "eu"}, "lat": "-21.0150290", "layout": "view", "lock": {"locked": false, "stealable": true}, "lon": "55.4610819", "mendizerra": "Reunion", "modified": "2024-10-20T16:16:46+00:00", "next_item": {}, "osm_kodea": "4404691554", "parent": {"@id": "https://312.deporeibar.com/mendiak", "@type": "Document", "altuera": null, "created": "2024-02-19T19:25:17+00:00", "creators": ["admin"], "description": "", "egoera_igoera": null, "egoera_mendia": null, "eguna": null, "erreserbak": null, "image_field": null, "image_scales": {}, "lat": null, "lon": null, "mendizerra": null, "review_state": "published", "sektorea": null, "title": "Mendiak", "type_title": "Orria", "zailtasuna": null}, "previous_item": {}, "review_state": "published", "rights": "", "sektorea": "Reunion", "subjects": [], "title": "Roche \u00c9crite", "type_title": "Mendia", "version": "current", "working_copy": null, "working_copy_of": null, "zailtasuna": 1}