{"@components": {"actions": {"@id": "https://312.deporeibar.com/mendiak/turo-de-lhome/@actions"}, "aliases": {"@id": "https://312.deporeibar.com/mendiak/turo-de-lhome/@aliases"}, "breadcrumbs": {"@id": "https://312.deporeibar.com/mendiak/turo-de-lhome/@breadcrumbs"}, "contextnavigation": {"@id": "https://312.deporeibar.com/mendiak/turo-de-lhome/@contextnavigation"}, "navigation": {"@id": "https://312.deporeibar.com/mendiak/turo-de-lhome/@navigation"}, "navroot": {"@id": "https://312.deporeibar.com/mendiak/turo-de-lhome/@navroot"}, "types": {"@id": "https://312.deporeibar.com/mendiak/turo-de-lhome/@types"}, "workflow": {"@id": "https://312.deporeibar.com/mendiak/turo-de-lhome/@workflow"}}, "@id": "https://312.deporeibar.com/mendiak/turo-de-lhome", "@type": "Mendia", "UID": "24439ceebb94453b949f93b848141a9d", "allow_discussion": false, "altuera": 1706, "beste_izenak": "", "contributors": [], "created": "2024-03-20T18:01:54+00:00", "creators": ["106932265020763600836"], "description": "", "effective": "2024-03-20T19:01:58", "egoera": "eginda", "exclude_from_nav": false, "expires": null, "id": "turo-de-lhome", "image": null, "image_caption": null, "is_folderish": true, "items": [{"@components": {"actions": {"@id": "https://312.deporeibar.com/mendiak/turo-de-lhome/113159089340959216835-2024-03-28/@actions"}, "aliases": {"@id": "https://312.deporeibar.com/mendiak/turo-de-lhome/113159089340959216835-2024-03-28/@aliases"}, "breadcrumbs": {"@id": "https://312.deporeibar.com/mendiak/turo-de-lhome/113159089340959216835-2024-03-28/@breadcrumbs"}, "contextnavigation": {"@id": "https://312.deporeibar.com/mendiak/turo-de-lhome/113159089340959216835-2024-03-28/@contextnavigation"}, "navigation": {"@id": "https://312.deporeibar.com/mendiak/turo-de-lhome/113159089340959216835-2024-03-28/@navigation"}, "navroot": {"@id": "https://312.deporeibar.com/mendiak/turo-de-lhome/113159089340959216835-2024-03-28/@navroot"}, "types": {"@id": "https://312.deporeibar.com/mendiak/turo-de-lhome/113159089340959216835-2024-03-28/@types"}, "workflow": {"@id": "https://312.deporeibar.com/mendiak/turo-de-lhome/113159089340959216835-2024-03-28/@workflow"}}, "@id": "https://312.deporeibar.com/mendiak/turo-de-lhome/113159089340959216835-2024-03-28", "@type": "Igoera", "UID": "47f217877b684c1f9559d02d8c7073f1", "allow_discussion": false, "contributors": [], "created": "2024-03-28T14:32:41+00:00", "creators": ["113159089340959216835"], "description": "", "effective": null, "egindako_eguna": "2024-03-29", "egoera": {"title": "Eginda", "token": "eginda"}, "eguna": "2024-03-29", "exclude_from_nav": false, "expires": null, "id": "113159089340959216835-2024-03-28", "is_folderish": true, "language": "", "layout": "view", "lock": {"locked": false, "stealable": true}, "mendia_igo_duena": "Javi", "mendizaleak": "Ana Mallagaray\nArrate Gutierrez\nJavier Carballlo\nI\u00f1aki Osoro", "modified": "2024-04-26T17:35:03+00:00", "next_item": {}, "oharrak": "Haizeak ez bagaitu eruaten bihar igoko dugu", "parent": {"@id": "https://312.deporeibar.com/mendiak/turo-de-lhome", "@type": "Mendia", "altuera": 1706, "created": "2024-03-20T18:01:54+00:00", "creators": ["106932265020763600836"], "description": "", "egoera_igoera": null, "egoera_mendia": null, "eguna": null, "erreserbak": null, "image_field": null, "image_scales": {}, "lat": "41.7764861", "lon": "2.4348176", "mendizerra": "Montseny", "review_state": "published", "sektorea": "Montseny", "title": "Tur\u00f3 de l'Home", "type_title": "Mendia", "zailtasuna": 1}, "previous_item": {}, "review_state": "published", "rights": "", "subjects": [], "title": "113159089340959216835 - 2024-03-28", "type_title": "Igoera", "version": "current", "working_copy": null, "working_copy_of": null}], "items_total": 1, "language": {"title": "Euskara", "token": "eu"}, "lat": "41.7764861", "layout": "view", "lock": {"locked": false, "stealable": true}, "lon": "2.4348176", "mendizerra": "Montseny", "modified": "2024-03-29T19:00:50+00:00", "next_item": {}, "osm_kodea": "5126232285", "parent": {"@id": "https://312.deporeibar.com/mendiak", "@type": "Document", "altuera": null, "created": "2024-02-19T19:25:17+00:00", "creators": ["admin"], "description": "", "egoera_igoera": null, "egoera_mendia": null, "eguna": null, "erreserbak": null, "image_field": null, "image_scales": {}, "lat": null, "lon": null, "mendizerra": null, "review_state": "published", "sektorea": null, "title": "Mendiak", "type_title": "Orria", "zailtasuna": null}, "previous_item": {}, "review_state": "published", "rights": "", "sektorea": "Montseny", "subjects": [], "title": "Tur\u00f3 de l'Home", "type_title": "Mendia", "version": "current", "working_copy": null, "working_copy_of": null, "zailtasuna": 1}